[{"ace":0,"service error":0,"attack error":0,"assist error":0,"defense error":0,"zero assist":0,"kill":3,"zero serve":0,"number":13,"successful dig":0,"block error":0,"grade":12,"name":"Dongjin","zero attack":0,"assist":0,"zero block":0,"block":0,"email":"idk@gmail.com"},{"ace":0,"service error":0,"attack error":0,"assist error":0,"defense error":0,"zero assist":0,"kill":0,"zero serve":0,"number":7,"successful dig":0,"block error":0,"grade":12,"name":"Zaida","zero attack":0,"assist":0,"zero block":0,"block":0,"email":"coolkid@gmail.com"},{"ace":0,"service error":0,"attack error":0,"assist error":0,"defense error":0,"zero assist":0,"kill":9001,"zero serve":0,"number":9,"successful dig":0,"block error":0,"grade":12,"name":"Andreas","zero attack":0,"assist":0,"zero block":0,"block":0,"email":"idkcoolckddddd@gmail.com"},{"ace":0,"service error":0,"attack error":0,"assist error":0,"defense error":0,"zero assist":0,"kill":0,"zero serve":0,"number":13,"successful dig":0,"block error":0,"grade":12,"name":"Omar","zero attack":2,"assist":0,"zero block":0,"block":0,"email":"g@gmail.com"}]